hype/LICENSE
hype/__init__.py
hype/asyncio/__init__.py
hype/asyncio/element.py
hype/element.py
hype/py.typed
hype_html-2.1.2.dist-info/LICENSE
hype_html-2.1.2.dist-info/METADATA
hype_html-2.1.2.dist-info/WHEEL
hype_html-2.1.2.dist-info/RECORD
